ez_setup.py
setup.py
django_sproutcore.egg-info/PKG-INFO
django_sproutcore.egg-info/SOURCES.txt
django_sproutcore.egg-info/SOURCES.txt~
django_sproutcore.egg-info/dependency_links.txt
django_sproutcore.egg-info/top_level.txt
djangocore/__init__.py
djangocore/decorators.py
djangocore/handlers.py
djangocore/urls.py
djangocore/utils.py
djangocore/transform/__init__.py
djangocore/transform/ae.py
djangocore/transform/base.py
djangocore/transform/dj.py
polls/__init__.py
polls/admin.py
polls/models.py
polls/urls.py
polls/views.py
sproutcore/__init__.py
sproutcore/apps/admin/core.js
sproutcore/apps/admin/main.js
sproutcore/apps/admin/english.lproj/main_page.js