Metadata-Version: 1.0
Name: django-sproutcore
Version: 0.7.3
Summary: A package to help automate creation of sproutcore apps for django
Home-page: http://github.com/erichocean/django-sproutcore/tree/master
Author: Taavi Taijala, Richard Silver, Erich Ocean
Author-email: taavi@taijala.com, corn13read@gmail.com, eric.ocean@me.com
License: BSD
Platform: UNKNOWN
Classifier: Development Status :: 4 - Beta
Classifier: Framework :: Django
Classifier: Intended Audience :: Developers
Classifier: License :: OSI Approved :: BSD License
Classifier: Operating System :: OS Independent
Classifier: Programming Language :: Python
Classifier: Topic :: Internet :: WWW/HTTP
